[
    {
        "title_index": "2",
        "video_channel": "Quality Of English Life",
        "title_en": "",
        "title_ja": "英語で楽しむ世界の名作「星の王子さま：The Little Prince」Chapter7【英語字幕・日本語字幕】",
        "video_id": "7I9QwGNMGt0"
    },
    {
        "title_index": "4",
        "video_channel": "Quality Of English Life",
        "title_en": "",
        "title_ja": "英語で楽しむ世界の名作「星の王子さま：The Little Prince」Chapter 6【英語字幕・日本語字幕】",
        "video_id": "Z0WdDgU1DIg"
    },
    {
        "title_index": "5",
        "video_channel": "Quality Of English Life",
        "title_en": "",
        "title_ja": "英語で楽しむ世界の名作「星の王子さま：The Little Prince」Chapter 5【英語字幕・日本語字幕】",
        "video_id": "AMLt7ek-Z2U"
    },
    {
        "title_index": "6",
        "video_channel": "Quality Of English Life",
        "title_en": "",
        "title_ja": "英語で楽しむ世界の名作「星の王子さま：The Little Prince」Chapter 4【英語字幕・日本語字幕】",
        "video_id": "8IvH7Dlf2gU"
    },
    {
        "title_index": "7",
        "video_channel": "Quality Of English Life",
        "title_en": "",
        "title_ja": "英語で楽しむ世界の名作「星の王子さま：The Little Prince」Chapter 3【英語字幕・日本語字幕】",
        "video_id": "_iXawvjU3IQ"
    },
    {
        "title_index": "8",
        "video_channel": "Quality Of English Life",
        "title_en": "",
        "title_ja": "英語で楽しむ世界の名作「星の王子さま：The Little Prince」Chapter 2【英語字幕・日本語字幕】",
        "video_id": "VdHvKJl0Qkk"
    },
    {
        "title_index": "9",
        "video_channel": "Quality Of English Life",
        "title_en": "",
        "title_ja": "英語で楽しむ世界の名作「星の王子さま：The Little Prince」Chapter 1【英語字幕・日本語字幕】",
        "video_id": "0Z69f2S9jzI"
    }
]